remote_config_fetcher/__init__.py
remote_config_fetcher/fetcher.py
remote_config_fetcher-0.1.1.dist-info/LICENSE.md
remote_config_fetcher-0.1.1.dist-info/METADATA
remote_config_fetcher-0.1.1.dist-info/WHEEL
remote_config_fetcher-0.1.1.dist-info/top_level.txt
remote_config_fetcher-0.1.1.dist-info/RECORD
