Metadata-Version: 2.1
Name: remote-config-fetcher
Version: 0.1.1
Summary: A package to fetch Firebase RemoteConfig values
Home-page: https://github.com/colo-o
Author: Steven Anaya
Author-email: stvanayar@gmail.com
License: UNKNOWN
Platform: UNKNOWN
Classifier: Programming Language :: Python :: 3
Classifier: License :: OSI Approved :: MIT License
Classifier: Operating System :: OS Independent
Requires-Python: >=3.6
License-File: LICENSE.md
Requires-Dist: firebase-admin
